cell_eval/__init__.py
cell_eval/__main__.py
cell_eval/_baseline.py
cell_eval/_evaluator.py
cell_eval/_score.py
cell_eval/data.py
cell_eval/py.typed
cell_eval/utils.py
cell_eval/_cli/__init__.py
cell_eval/_cli/_baseline.py
cell_eval/_cli/_const.py
cell_eval/_cli/_prep.py
cell_eval/_cli/_run.py
cell_eval/_cli/_score.py
cell_eval/_pipeline/__init__.py
cell_eval/_pipeline/_runner.py
cell_eval/_types/__init__.py
cell_eval/_types/_anndata.py
cell_eval/_types/_de.py
cell_eval/_types/_enums.py
cell_eval/metrics/__init__.py
cell_eval/metrics/_anndata.py
cell_eval/metrics/_de.py
cell_eval/metrics/_impl.py
cell_eval/metrics/_registry.py
cell_eval/metrics/base.py
cell_eval-0.6.8.dist-info/METADATA
cell_eval-0.6.8.dist-info/WHEEL
cell_eval-0.6.8.dist-info/entry_points.txt
cell_eval-0.6.8.dist-info/licenses/LICENSE
cell_eval-0.6.8.dist-info/RECORD
