Metadata-Version: 2.4
Name: cell-eval
Version: 0.6.8
Summary: Evaluation metrics for single-cell perturbation predictions
Author-email: Noam Teyssier <noam.teyssier@arcinstitute.org>, Abhinav Adduri <abhinav.adduri@arcinstitute.org>, Yusuf Roohani <yusuf.roohani@arcinstitute.org>
License-File: LICENSE
Requires-Python: <3.13,>=3.10
Requires-Dist: igraph>=0.11.8
Requires-Dist: pdex>=0.1.26
Requires-Dist: polars>=1.30.0
Requires-Dist: pyarrow>=18.0.0
Requires-Dist: pyyaml>=6.0.2
Requires-Dist: scanpy>=1.10.3
Requires-Dist: tqdm>=4.67.1
